docstrings2pep727-0.2.0.dist-info/METADATA
docstrings2pep727-0.2.0.dist-info/WHEEL
docstrings2pep727-0.2.0.dist-info/entry_points.txt
docstrings2pep727-0.2.0.dist-info/licenses/LICENSE
docstrings2pep727/__init__.py
docstrings2pep727/__main__.py
docstrings2pep727/cli.py
docstrings2pep727/debug.py
docstrings2pep727/py.typed
docstrings2pep727/transformer.py
docstrings2pep727-0.2.0.dist-info/RECORD
