Metadata-Version: 2.1
Name: docstrings2pep727
Version: 0.2.0
Summary: Move documentation from docstrings to PEP 727 type annotations.
Author-Email: Timothée Mazzucotelli <pawamoy@pm.me>
License: ISC
Classifier: Development Status :: 4 - Beta
Classifier: Intended Audience :: Developers
Classifier: Programming Language :: Python
Classifier: Programming Language :: Python :: 3
Classifier: Programming Language :: Python :: 3 :: Only
Classifier: Programming Language :: Python :: 3.8
Classifier: Programming Language :: Python :: 3.9
Classifier: Programming Language :: Python :: 3.10
Classifier: Programming Language :: Python :: 3.11
Classifier: Programming Language :: Python :: 3.12
Classifier: Topic :: Documentation
Classifier: Topic :: Software Development
Classifier: Topic :: Utilities
Classifier: Typing :: Typed
Project-URL: Homepage, https://pawamoy.github.io/docstrings2pep727
Project-URL: Documentation, https://pawamoy.github.io/docstrings2pep727
Project-URL: Changelog, https://pawamoy.github.io/docstrings2pep727/changelog
Project-URL: Repository, https://github.com/pawamoy/docstrings2pep727
Project-URL: Issues, https://github.com/pawamoy/docstrings2pep727/issues
Project-URL: Discussions, https://github.com/pawamoy/docstrings2pep727/discussions
Project-URL: Gitter, https://gitter.im/docstrings2pep727/community
Project-URL: Funding, https://github.com/sponsors/pawamoy
Requires-Python: >=3.8
Requires-Dist: libcst>=1.0.1
Requires-Dist: griffe>=0.35.2
